wiki_synonyms/__init__.py
wiki_synonyms/data_worker.py
wiki_synonyms/paths.py
wiki_synonyms/data/__init__.py
wiki_synonyms/data/synonyms_1.json
wiki_synonyms/data/synonyms_2.json
wiki_synonyms/data/synonyms_3.json
wiki_synonyms/data/synonyms_4.json
wiki_synonyms/data_index/__init__.py
wiki_synonyms/data_index/index_builder.py
wiki_synonyms-0.5.0.data/data/wiki_synonyms.data/synonyms_1.json
wiki_synonyms-0.5.0.data/data/wiki_synonyms.data/synonyms_2.json
wiki_synonyms-0.5.0.data/data/wiki_synonyms.data/synonyms_3.json
wiki_synonyms-0.5.0.data/data/wiki_synonyms.data/synonyms_4.json
wiki_synonyms-0.5.0.dist-info/LICENSE
wiki_synonyms-0.5.0.dist-info/METADATA
wiki_synonyms-0.5.0.dist-info/WHEEL
wiki_synonyms-0.5.0.dist-info/top_level.txt
wiki_synonyms-0.5.0.dist-info/RECORD
