Metadata-Version: 2.1
Name: wiki_synonyms
Version: 0.5.0
Summary: Python package for Wiki synonyms
Home-page: https://github.com/iis-research-team/wiki-synonyms
Author: IIS Research Team
Author-email: bruches@bk.ru
License: MIT
License-File: LICENSE
Requires-Dist: numpy
